p4_data_ingestion/__init__.py
p4_data_ingestion/_nbdev.py
p4_data_ingestion/coordinates.py
p4_data_ingestion/input.py
p4_data_ingestion/manifests.py
p4_data_ingestion/tiling.py
p4_data_ingestion-0.2.0.dist-info/LICENSE
p4_data_ingestion-0.2.0.dist-info/METADATA
p4_data_ingestion-0.2.0.dist-info/WHEEL
p4_data_ingestion-0.2.0.dist-info/entry_points.txt
p4_data_ingestion-0.2.0.dist-info/top_level.txt
p4_data_ingestion-0.2.0.dist-info/RECORD
